stpt2zarr/__init__.py
stpt2zarr/stptlib/__init__.py
stpt2zarr/stptlib/mosaicdict.py
stpt2zarr/stptlib/stptraw.py
stpt2zarr/stptlib/stptsectionraw.py
stpt2zarr/stptlib/stpttileraw.py
stpt2zarr-0.2.2.dist-info/METADATA
stpt2zarr-0.2.2.dist-info/WHEEL
stpt2zarr-0.2.2.dist-info/entry_points.txt
stpt2zarr-0.2.2.dist-info/top_level.txt
stpt2zarr-0.2.2.dist-info/RECORD
