Metadata-Version: 2.2
Name: stpt2zarr
Version: 0.2.2
Summary: STPT scan to Zarr conversion
Home-page: https://gitlab.developers.cam.ac.uk/astronomy/camcead/imaxt/stpt2zarr
Author: Mo Alsad and Eduardo Gonzalez Solares
Author-email: "msa51@cam.ac.uk
Project-URL: Bug Tracker, https://gitlab.developers.cam.ac.uk/astronomy/camcead/imaxt/stpt2zarr/-/issues
Classifier: Programming Language :: Python :: 3
Classifier: License :: OSI Approved :: MIT License
Classifier: Operating System :: OS Independent
Requires-Python: >=3.7
Requires-Dist: numpy
Requires-Dist: click
Requires-Dist: dask
Requires-Dist: distributed
Requires-Dist: imaxt_image
Requires-Dist: python_dateutil
Requires-Dist: xarray
Requires-Dist: zarr
